[
  {
    "id": "tt0974005",
    "streams": [
      {
        "magnetLink": "magnet:?xt=urn:btih:3df148b027619d7bca85afa14841fb08ccec20bc",
        "filename": "[apreder]Inconceivable(2008)DVB.mkv",
        "websiteTitle": "Немыслимый / Непостижимо / Inconceivable [2008 DVB] MVO (Студия Акцент) + Original (Eng)",
        "quality": "",
        "size": "1.77 GB"
      }
    ],
    "originalTitle": "Inconceivable",
    "addedAt": "2024-11-21T17:27:48.230Z",
    "lastUpdated": "2024-11-21T17:27:48.230Z"
  },
  {
    "id": "tt0468569",
    "streams": [
      {
        "magnetLink": "magnet:?xt=urn:btih:dfa72b42e989abadd926f2a6046e46b62fac3e01",
        "filename": "The.Dark.Knight.2008.IMAX.4K.HDR.DV.2160p.BDRemux Ita Eng x265-NAHOM.mkv",
        "websiteTitle": "The.Dark.Knight.2008.IMAX.4K.HDR.DV.2160p.BDRemux Ita Eng x265-NAHOM",
        "quality": "4k",
        "size": "51.36 GB"
      },
      {
        "magnetLink": "magnet:?xt=urn:btih:3e58c70a4cb4f5504adf808aa8f276f227d74169",
        "filename": "The.Dark.Knight.2008.UHD.BluRay.2160p.TrueHD.5.1.DV.HEVC.HYBRID.REMUX-FraMeSToR.mkv",
        "websiteTitle": "The Dark Knight 2008 UHD BluRay 2160p TrueHD 5 1 DV HEVC HYBRID REMUX-FraMeSToR",
        "quality": "4k",
        "size": "53.75 GB"
      },
      {
        "magnetLink": "magnet:?xt=urn:btih:a5fc2e0ac62e290c9c62fbd47a2462e96a84f52c",
        "filename": "The.Dark.Knight.2008.2160p.UHD.BluRay.X265-IAMABLE.mkv",
        "websiteTitle": "The.Dark.Knight.2008.2160p.UHD.BluRay.x265.10bit.HDR.DTS-HD.MA.5",
        "quality": "4k",
        "size": "21.57 GB"
      },
      {
        "magnetLink": "magnet:?xt=urn:btih:2de4f8a3253098a3895d4381bbcdc36ba4bda644",
        "filename": "The.Dark.Knight.2008.2160p.UHD.BDRip.HDR.DV.x265.DD+5.1-DVT.mkv",
        "websiteTitle": "Темный рыцарь / The Dark Knight (2008) UHD BDRip 2160p | 4K | HDR | Dolby Vision Profile 8 | IMAX | D P A L1",
        "quality": "4k",
        "size": "37.22 GB"
      },
      {
        "magnetLink": "magnet:?xt=urn:btih:73f2b9287cf38697e23e508cc8504dc35be51ea1",
        "filename": "The.Dark.Knight.2008.IMAX.BluRay.2160p.x265.HDR.DD.5.1[En.Hi]-DTOne.mkv",
        "websiteTitle": "The.Dark.Knight.2008.IMAX.BluRay.2160p.x265.HDR.DD.5.1[En.Hi]-DT",
        "quality": "4k",
        "size": "22.88 GB"
      },
      {
        "magnetLink": "magnet:?xt=urn:btih:759ca07141be32f7bad81eccb3a2e914066c680f",
        "filename": "The.Dark.Knight.2008.IMAX.2160p.10bit.HDR.DV.BluRay.6CH.x265.HEVC-PSA.mkv",
        "websiteTitle": "The.Dark.Knight.2008.IMAX.2160p.10bit.HDR.DV.BluRay.6CH.x265.HEVC-PSA",
        "quality": "4k",
        "size": "5.68 GB"
      },
      {
        "magnetLink": "magnet:?xt=urn:btih:6ae0ed5ab38c545dd2ad37556c29e356e0d21ade",
        "filename": "The.Dark.Knight.2008.Bluray.2160p.AV1.HDR10.OPUS.5.1-UH.mkv",
        "websiteTitle": "The Dark Knight 2008 Bluray IMAX 2160p AV1 HDR10 EN/ITA/FR/ES OPUS.5.1-UH [UserHEVC]",
        "quality": "4k",
        "size": "9.54 GB"
      },
      {
        "magnetLink": "magnet:?xt=urn:btih:a8d8f67cd535dcbccbfceaf182a68c1a910ff30e",
        "filename": "Il cavaliere oscuro - The Dark Knight (2008) ITA.ENG IMAX 2160p H265 HDR10 sub NUita.eng Sp33dy94-MIRCrew.mkv",
        "websiteTitle": "Il Cavaliere oscuro Trilogia (2005-2012) IMAX 2160p H265 HDR10 ITA.ENG sub NUitaeng Sp33dy94 MIRCrew",
        "quality": "4k",
        "size": "4.12 GB"
      },
      {
        "magnetLink": "magnet:?xt=urn:btih:e7d4d6a669459da1e0a554b2e867d1cb97b6a00d",
        "filename": "The.Dark.Knight.2008.Eng.Fre.Ger.Ita.Por.Spa.Cze.Hun.Pol.Rus.Tha.Jpn.2160p.BluRay.Hybrid.Remux.DV.HDR.HEVC.DTS-HD.MA-SGF.mkv",
        "websiteTitle": "The.Dark.Knight.2008.Eng.Fre.Ger.Ita.Por.Spa.Cze.Hun.Pol.Rus.Tha.Jpn.2160p.BluRay.Hybrid.Remux.DV.HDR.HEVC.DTS-HD.MA-SGF",
        "quality": "4k",
        "size": "66.28 GB"
      },
      {
        "magnetLink": "magnet:?xt=urn:btih:03bdfe302b3cb454910f3bd8bcf8d01e92cbac37",
        "filename": "The.Dark.Knight.2008.2160p.UHD.BluRay.10bit.HDR.x265-HazMatt.mkv",
        "websiteTitle": "The.Dark.Knight.2008.2160p.UHD.BluRay.10bit.HDR.x265-HazMatt.mkv",
        "quality": "4k",
        "size": "4.09 GB"
      },
      {
        "magnetLink": "magnet:?xt=urn:btih:1e0dfa99ba80cb28a23b97cb72482d4bda0c84e5",
        "filename": "02-The.Dark.Knight.2008.2160p.UHD.HDR.BluRay.(x265 10bit AAC5.1).Dual Audio. WWW.BLUDV.COM.mkv",
        "websiteTitle": "Triologia Batman o Cavaleiro das Trevas 4k Dual Áudio WWW.BLUDV.COM",
        "quality": "4k",
        "size": "5.89 GB"
      },
      {
        "magnetLink": "magnet:?xt=urn:btih:61be42fb337b1b84f844b88fd904982a0a2330e3",
        "filename": "The.Dark.Knight.2008.2160p.4K.BluRay.x265.10bit.AAC5.1-[YTS.MX].mkv",
        "websiteTitle": "The Dark Knight (2008) [2160p] [4K] [BluRay] [5.1] [YTS] [YIFY]",
        "quality": "4k",
        "size": "7.52 GB"
      },
      {
        "magnetLink": "magnet:?xt=urn:btih:d2e2b4974ce3340fc06dad26bc0b66b792fce870",
        "filename": "The.Dark.Knight.2008.2160p.BluRay.REMUX.HEVC.DTS-HD.MA.5.1-FGT.mkv",
        "websiteTitle": "The.Dark.Knight.2008.2160p.BluRay.REMUX.HEVC.DTS-HD.MA.5.1-FGT",
        "quality": "4k",
        "size": "63.11 GB"
      },
      {
        "magnetLink": "magnet:?xt=urn:btih:f51981972923aef6d821141efad743458dad3895",
        "filename": "The Dark Knight 2008 2160p Bluray x265 AC3 DTS-KiNGDOM.mkv",
        "websiteTitle": "The Dark Knight 2008 2160p Bluray x265 AC3 DTS-KiNGDOM",
        "quality": "4k",
        "size": "13.32 GB"
      },
      {
        "magnetLink": "magnet:?xt=urn:btih:66672b822002b6f19af478fb7c886787afee5f9f",
        "filename": "Batman.The.Dark.Knight.2008.1080p.BluRay.x264.YIFY.mp4",
        "websiteTitle": "Imdb top 263 movies hindi english gdrive",
        "quality": "1080p",
        "size": "1.7 GB"
      },
      {
        "magnetLink": "magnet:?xt=urn:btih:a54926c2e07b0e5f0243954330b599b31c804f0b",
        "filename": "Batman.The.Dark.Knight.2008.1080p.BluRay.x264.YIFY.mp4",
        "websiteTitle": "The Dark Knight (2008) 1080p BluRay x264 - 1.7GB - YIFY",
        "quality": "1080p",
        "size": "1.7 GB"
      },
      {
        "magnetLink": "magnet:?xt=urn:btih:d65e4ea7c6404a026266da6b2845fe94cb9ce100",
        "filename": "The Dark Knight (2008) 1080p PROPER Bluray 10-bit x265 HEVC TrueHD AC3 5.1 [XannyFamily].mkv",
        "websiteTitle": "The Dark Knight (2008) 1080p PROPER Bluray 10-bit x265 HEVC TrueHD AC3 5.1 [XannyFamily]",
        "quality": "1080p",
        "size": "8.39 GB"
      },
      {
        "magnetLink": "magnet:?xt=urn:btih:fd43bdd56532c5464ed7801e2f26cda981534498",
        "filename": "The Dark Knight [2008] 1080p BDRip x265 TrueHD 5.1 Kira [SEV].mkv",
        "websiteTitle": "The Dark Knight [2008] 1080p BDRip x265 TrueHD 5.1 Kira [SEV]",
        "quality": "1080p",
        "size": "15.37 GB"
      },
      {
        "magnetLink": "magnet:?xt=urn:btih:28fb373db2c936015e967544e50a7bffdbb5d3a1",
        "filename": "The.Dark.Knight.2008.1080p.BluRay.DDP5.1.x265.10bit-GalaxyRG265.mkv",
        "websiteTitle": "The.Dark.Knight.2008.1080p.BluRay.DDP5.1.x265.10bit-GalaxyRG265",
        "quality": "1080p",
        "size": "4.02 GB"
      },
      {
        "magnetLink": "magnet:?xt=urn:btih:536023f3aed2142df575f376b8f778175c8ede56",
        "filename": "The.Dark.Knight.2008.BDRip.1080p.Rus.Eng.mkv",
        "websiteTitle": "Темный рыцарь / The Dark Knight (2008) BDRip 1080p | IMAX",
        "quality": "1080p",
        "size": "7.76 GB"
      },
      {
        "magnetLink": "magnet:?xt=urn:btih:a3b5fdd23c3803a0287ca5c5a3e4b126e855ff98",
        "filename": "The Dark Knight 2008 IMAX BluRay 1080p DTS AC3 x264-MgB.mkv",
        "websiteTitle": "The Dark Knight 2008 IMAX BluRay 1080p DTS AC3 x264-MgB",
        "quality": "1080p",
        "size": "9.96 GB"
      },
      {
        "magnetLink": "magnet:?xt=urn:btih:c9e12910f835903f67d35bcf7f5b568a11b1d6ca",
        "filename": "Batman - O Cavaleiro das Trevas 1080p (2008) Dual Áudio BluRay 5.1 -- Lucas Firmo.mkv",
        "websiteTitle": "Trilogia Cavaleiro das Trevas 1080p (2005 - 2012) Dual Áudio BluRay 5.1 -- By - Lucas Firmo",
        "quality": "1080p",
        "size": "2.72 GB"
      },
      {
        "magnetLink": "magnet:?xt=urn:btih:e7c2571e97b4f3937f2c3d2d1954b11ca8ef12de",
        "filename": "Batman The Dark Knight 2008 (1080p x265 Joy).m4v",
        "websiteTitle": "Batman The Dark Knight 2008 (1080p X265 HEVC AAC 5.1 Joy) [UTR]",
        "quality": "1080p",
        "size": "1.87 GB"
      },
      {
        "magnetLink": "magnet:?xt=urn:btih:2861abae0bfc59a754d83b70eecb1b142198763f",
        "filename": "The.Dark.Knight.2008.1080p.BluRay.H264.AAC-RARBG.mp4",
        "websiteTitle": "500 Classic Movies Part 1 of 7 - 67 Movies with IMDB Ratings from 8.0 to 9.0 jZQ 196GB Nb8",
        "quality": "1080p",
        "size": "2.9 GB"
      },
      {
        "magnetLink": "magnet:?xt=urn:btih:17d9a881623c5d9d328cc4676a283c61ad5e85e7",
        "filename": "The Dark Knight (2008) IMAX Bluray [AV1 1080p 10bit OPUS 5.1] [SKYLake].mkv",
        "websiteTitle": "The Dark Knight (2008) 1080p IMAX BluRay AV1 10bit Opus 5.1 [SKYLake]",
        "quality": "1080p",
        "size": "2.81 GB"
      },
      {
        "magnetLink": "magnet:?xt=urn:btih:30584c3c430158140e09d62fa67fad82b852c15b",
        "filename": "The Dark Knight (2008) IMAX 1080p 10bit BluRay HEVC x265 [Hindi NF HE-AAC 2.0 128kbps _ English AAC 5.1] ESub _ R∆G∆ _ PSA.mkv",
        "websiteTitle": "The Dark Knight (2008) IMAX 1080p 10bit BluRay NEW DUB [Hindi NF AAC English AAC 5.1] Dual Audio x265 HEVC ESub _ R∆G∆ [ProtonMovies]",
        "quality": "1080p",
        "size": "3.59 GB"
      },
      {
        "magnetLink": "magnet:?xt=urn:btih:466b4abccee26bd97234ea0d20d0771c960165a9",
        "filename": "The.Dark.Knight.2008.IMAX.1080p.BluRay.DDP.5.1.H.265-EDGE2020.mkv",
        "websiteTitle": "The Dark Knight 2008 IMAX 1080p BluRay DD+ 5.1 x265-edge2020",
        "quality": "1080p",
        "size": "4.33 GB"
      },
      {
        "magnetLink": "magnet:?xt=urn:btih:6d6299065dbcf374b5a7d8564e4a6540b80b9c67",
        "filename": "[ OxTorrent.cc ] The Dark Knight.2008.1080p.MULTi BluRay x264-PopHD.mkv",
        "websiteTitle": "The Dark Knight.2008.1080p.MULTi BluRay x264-PopHD",
        "quality": "1080p",
        "size": "3.29 GB"
      },
      {
        "magnetLink": "magnet:?xt=urn:btih:3ef7e04f3c6e00e2621ea2ad9ad19440f2891c10",
        "filename": "DK2 The Dark Knight (2008) 1080p Surround.mp4",
        "websiteTitle": "Amazing Films 11 - Mp4 x264 AC3 1080p",
        "quality": "1080p",
        "size": "4.43 GB"
      },
      {
        "magnetLink": "magnet:?xt=urn:btih:a581e22f402ad6ebc47481a4503865fd0468f784",
        "filename": "The.Dark.Knight.2008.1080p.BluRay.DD5.1.x265-POIASD.mkv",
        "websiteTitle": "The.Dark.Knight.Trilogy.2005-2012.1080p.BluRay.DD5.1.x265-POIASD",
        "quality": "1080p",
        "size": "7.06 GB"
      },
      {
        "magnetLink": "magnet:?xt=urn:btih:d6d8261c22c03b79a853a727e53e8108b33e96b2",
        "filename": "The Dark Knight 2008 IMAX BluRay 1080p DTS-HD MA 5.1 AC3 x264-MgB.mkv",
        "websiteTitle": "The Dark Knight 2008 IMAX BluRay 1080p DTS-HD MA AC3 x264-MgB",
        "quality": "1080p",
        "size": "10.7 GB"
      },
      {
        "magnetLink": "magnet:?xt=urn:btih:6a6796cc3a915416f0120a15e4a9942d6c41f702",
        "filename": "The Dark Knight (2008) 1080p BluRay AV1 Opus Multi12 [GRAV1TY].mkv",
        "websiteTitle": "The Dark Knight (2008) 1080p BluRay AV1 Opus Multi12 [GRAV1TY]",
        "quality": "1080p",
        "size": "6.24 GB"
      },
      {
        "magnetLink": "magnet:?xt=urn:btih:29f865ef4fb9e300a5f734f2818e6c56c045606a",
        "filename": "The Dark Knight 2008 1080p AMZN WEB-DL H264 Multi Audios DDP 2.0 D0T-Telly.mkv",
        "websiteTitle": "The Dark Knight 2008 1080p AMZN WEB-DL H264 Multi Audios DDP 2.0 D0T-Telly",
        "quality": "1080p",
        "size": "10.2 GB"
      },
      {
        "magnetLink": "magnet:?xt=urn:btih:c478a5d415faa9684b21d9652535b5c100a27777",
        "filename": "The Dark Knight (2008) IMAX 1080p 10bit Bluray x265 HEVC [Org DD 2.0 Hindi + DD 5.1 English] ESub ~ TombDoc.mkv",
        "websiteTitle": "The Dark Knight Trilogy (2005-2012) IMAX 1080p 10bit Bluray x265 HEVC [Org DD 2.0 - DD 5.1 Hindi DD 5.1 English] MSubs ~ TombDoc",
        "quality": "1080p",
        "size": "4.99 GB"
      },
      {
        "magnetLink": "magnet:?xt=urn:btih:b3009b70c71ac33ff39b4dbb55bd7c80995a04fb",
        "filename": "The Dark Knight 2008 BDRip ITA ENG 1080p x265 Paso77.mkv",
        "websiteTitle": "The Dark Knight (2008 ITA/ENG) [1080p x265] [Paso77]",
        "quality": "1080p",
        "size": "3.78 GB"
      },
      {
        "magnetLink": "magnet:?xt=urn:btih:157de2ebe06bafb043b0d54e2e7eef3aa86e6575",
        "filename": "The.Dark.Knight.(2008).1080p.BluRay.10-bit.x265.DTS.5.1 Qman[UTR].mkv",
        "websiteTitle": "The Dark Knight (2008) (1080p BluRay 10bit x265 HEVC DTS 5.1 Qman) [UTR]",
        "quality": "1080p",
        "size": "4.2 GB"
      },
      {
        "magnetLink": "magnet:?xt=urn:btih:7b9ce080bf7e584b0e75da3e60a5e3c1d5ca876c",
        "filename": "Batman.Il.Cavaliere.Oscuro.2008.BluRay-mux.ITA.ENG.AC3.1080p.x264[Carnil91].mkv",
        "websiteTitle": "Il Cavaliere Oscuro 2008 BluRay-mux ITA ENG AC3 1080p X264 [Carnil91] [TNT Village]",
        "quality": "1080p",
        "size": "2.79 GB"
      },
      {
        "magnetLink": "magnet:?xt=urn:btih:3aa61d8a2debf9aa6625eb4d4f0df28a1901a970",
        "filename": "Il Cavaliere Oscuro - The Dark Knight IMAX (2008) 1080p H265 ita eng AC3 5.1 sub ita eng Licdom.mkv",
        "websiteTitle": "Il Cavaliere Oscuro - The Dark Knight IMAX (2008) 1080p H265 ita eng AC3 5.1 sub ita eng Licdom.mkv",
        "quality": "1080p",
        "size": "3.14 GB"
      },
      {
        "magnetLink": "magnet:?xt=urn:btih:24723cdb1508e12421a36ed66322e154e3c9a653",
        "filename": "The.Dark.Knight.2008.IMAX.1080p.BluRay.10bit.HEVC.6CH.MkvCage.ws.mkv",
        "websiteTitle": "The.Dark.Knight.2008.IMAX.1080p.BluRay.10bit.HEVC.6CH.MkvCage",
        "quality": "1080p",
        "size": "4.04 GB"
      },
      {
        "magnetLink": "magnet:?xt=urn:btih:921b85a8c84cf32b0594f8f67428291daa465f03",
        "filename": "O.Cavaleiro.das.Trevas.Parte.2.mkv",
        "websiteTitle": "DC Comics - Animated Original Movies Collection 1993 - 2013 720p",
        "quality": "720p",
        "size": "2.3 GB"
      },
      {
        "magnetLink": "magnet:?xt=urn:btih:921b85a8c84cf32b0594f8f67428291daa465f03",
        "filename": "O.Cavaleiro.das.Trevas.Parte.1.mkv",
        "websiteTitle": "DC Comics - Animated Original Movies Collection 1993 - 2013 720p",
        "quality": "720p",
        "size": "2.3 GB"
      },
      {
        "magnetLink": "magnet:?xt=urn:btih:9190ac70ad666ba19777c19a2ad3e44f46cd8e6e",
        "filename": "The Dark Knight 2008 720p BluRay x264 Ganool.mkv",
        "websiteTitle": "Batman Collection (8 Films) 1989-2016 720p BluRay x264 Ganool",
        "quality": "720p",
        "size": "1.2 GB"
      },
      {
        "magnetLink": "magnet:?xt=urn:btih:8c781b416862f04e14c19cb1e0041f42499d2fed",
        "filename": "The.Dark.Knight.2008.IMAX.720p.10bit.BluRay.6CH.x265.HEVC-PSA.mkv",
        "websiteTitle": "The.Dark.Knight.2008.IMAX.720p.10bit.BluRay.6CH.x265.HEVC-PSA",
        "quality": "720p",
        "size": "1.62 GB"
      },
      {
        "magnetLink": "magnet:?xt=urn:btih:ea6c6745344cb14e67ec4cdf7962ee900b1af45f",
        "filename": "The.Dark.Knight.2008_MVO_HDRip_[scarabey.org].avi",
        "websiteTitle": "Темный рыцарь / The Dark Knight (2008) HDRip от Scarabey | P",
        "quality": "",
        "size": "1.45 GB"
      },
      {
        "magnetLink": "magnet:?xt=urn:btih:4986ace2ee7a564508e0d5cfdde2d9018b8af942",
        "filename": "Batman The Dark Knight [2008] dvd rip nlx.avi",
        "websiteTitle": "Official IMDb Top 250 Movies Collection 6/17/2011",
        "quality": "",
        "size": "698.99 MB"
      },
      {
        "magnetLink": "magnet:?xt=urn:btih:3715e1b359ede29682395c056f1ffd182911048b",
        "filename": "The.Dark.Knight.Le.Chevalier.Noir.2008.MULTi.VFF.4KLight.HDR.10bits.x265.DTS-HD.MA-MenZo.mkv",
        "websiteTitle": "Batman.The.Dark.Knight.Saga.Complete.2005-2012.MULTi.VFF.4KLight.HDR.10bits.x265.DTS-HD.MA-MenZo",
        "quality": "4K",
        "size": "10.64 GB"
      },
      {
        "magnetLink": "magnet:?xt=urn:btih:ba8106fcca5108880f4a0182b37cfe0a693a6dd6",
        "filename": "[ OxTorrent.cc ] Batman.The.Dark.Knight.2008.VF.XViD-Ox.avi",
        "websiteTitle": "Batman.The.Dark.Knight.2008.VF.XViD-Ox",
        "quality": "",
        "size": "699.56 MB"
      }
    ],
    "originalTitle": "The Dark Knight",
    "addedAt": "2024-11-21T18:39:44.763Z",
    "lastUpdated": "2024-11-21T18:39:44.763Z"
  }
]